zxingcpp.cp313-win_amd64.pyd
zxing_cpp-2.3.0.dist-info/METADATA
zxing_cpp-2.3.0.dist-info/WHEEL
zxing_cpp-2.3.0.dist-info/top_level.txt
zxing_cpp-2.3.0.dist-info/RECORD
