Metadata-Version: 2.1
Name: zxing-cpp
Version: 2.3.0
Summary: Python bindings for the zxing-cpp barcode library
Home-page: https://github.com/zxing-cpp/zxing-cpp
Author: ZXing-C++ Community
Author-email: zxingcpp@gmail.com
License: Apache License 2.0
Keywords: barcode
Classifier: Development Status :: 4 - Beta
Classifier: Programming Language :: Python :: 3
Classifier: License :: OSI Approved :: Apache Software License
Classifier: Operating System :: OS Independent
Classifier: Topic :: Multimedia :: Graphics
Requires-Python: >=3.6
